pysecretcode/__init__.py
pysecretcode/core.py
pysecretcode-0.1.0.dist-info/licenses/LICENCE
pysecretcode-0.1.0.dist-info/METADATA
pysecretcode-0.1.0.dist-info/WHEEL
pysecretcode-0.1.0.dist-info/top_level.txt
pysecretcode-0.1.0.dist-info/RECORD
