Metadata-Version: 2.4
Name: PySecretCode
Version: 0.1.0
Summary: A Python package for various encryption and hashing algorithms
Home-page: https://github.com/yourusername/PySecretCode
Author: Eden Simamora
Author-email: Eden Simamora <aeden6877@gmail.com>
License: MIT
Requires-Python: >=3.9
License-File: LICENCE
Requires-Dist: cryptography
Requires-Dist: pycryptodome
Requires-Dist: colorama
Requires-Dist: rich
Requires-Dist: pyperclip
Requires-Dist: pyfiglet
Requires-Dist: termcolor
Requires-Dist: pyinstaller
Requires-Dist: wheel
Requires-Dist: setuptools
Requires-Dist: build
Requires-Dist: pycryptodomex
Requires-Dist: crcmod
Requires-Dist: argon2-cffi
Requires-Dist: mmh3
Requires-Dist: bcrypt
Dynamic: author
Dynamic: home-page
Dynamic: license-file
Dynamic: requires-python
